Metadata-Version: 2.3
Name: fuel_efficency
Version: 0.0.1
Summary: Tech challenge for Ambev
Project-URL: Homepage, https://github.com/SamuelAmicoFidelis/bees_ml_path_challenge-skeleton
Project-URL: Issues, https://github.com/SamuelAmicoFidelis/bees_ml_path_challenge-skeleton/issues
Author-email: Samuel Amico <sam.fst@gmail.com>
License-File: LICENSE
Classifier: License :: OSI Approved :: MIT License
Classifier: Operating System :: OS Independent
Classifier: Programming Language :: Python :: 3
Requires-Python: >=3.10
